MANIFEST.in
README.rst
monner.py
setup.py
monner.egg-info/PKG-INFO
monner.egg-info/SOURCES.txt
monner.egg-info/dependency_links.txt
monner.egg-info/entry_points.txt
monner.egg-info/requires.txt
monner.egg-info/top_level.txt