Metadata-Version: 1.0
Name: monner
Version: 0.3.0
Summary: Monitors the system whilst executing a given program
Home-page: https://github.com/colinhowe/monner
Author: Colin Howe
Author-email: colin@colinhowe.co.uk
License: Apache 2.0
Platform: UNKNOWN
Classifier: Development Status :: 4 - Beta
Classifier: License :: OSI Approved :: Apache Software License
Classifier: Operating System :: OS Independent
Classifier: Topic :: Utilities
